airtable_helper/__init__.py
airtable_helper-0.0.14.dist-info/licenses/LICENSE
airtable_helper-0.0.14.dist-info/METADATA
airtable_helper-0.0.14.dist-info/WHEEL
airtable_helper-0.0.14.dist-info/top_level.txt
airtable_helper-0.0.14.dist-info/RECORD
