Metadata-Version: 2.4
Name: airtable_helper
Version: 0.0.14
Summary: Simple class that helps dealing with airtable api
Author-email: shrank <info@murxs.ch>
License-Expression: CC0-1.0
Project-URL: Homepage, https://github.com/shrank/airtable-helper
Keywords: airtable
Classifier: Programming Language :: Python :: 3
Classifier: Operating System :: OS Independent
Requires-Python: >=3.0
License-File: LICENSE
Requires-Dist: pyairtable
Dynamic: license-file
